{
  "providers": {
    "awscloudformation": {
      "AuthRoleName": "a-20190102223756-authRole",
      "UnauthRoleArn": "arn:aws:iam::797353049590:role/a-20190102223756-unauthRole",
      "AuthRoleArn": "arn:aws:iam::797353049590:role/a-20190102223756-authRole",
      "Region": "us-east-1",
      "DeploymentBucketName": "a-20190102223756-deployment",
      "UnauthRoleName": "a-20190102223756-unauthRole",
      "StackName": "a-20190102223756",
      "StackId": "arn:aws:cloudformation:us-east-1:797353049590:stack/a-20190102223756/57833cb0-0f11-11e9-8d11-0e8cdcc47538"
    }
  },
  "api": {
    "FAST AppSync API": {
      "service": "AppSync",
      "output": {
        "securityType": "AMAZON_COGNITO_USER_POOLS",
        "GraphQLAPIIdOutput": "nuerz7qsw5cm7cjme4odwmesdy",
        "GraphQLAPIEndpointOutput": "https://klchv4y3efga5i6dydzloxaule.appsync-api.us-east-1.amazonaws.com/graphql"
      },
      "lastPushTimeStamp": "2019-01-03T04:39:01.682Z"
    }
  }
}